[{"worker_response":{"json_result":"{\"body\": {\"latency\": 8.769861221313477, \"cold\": true, \"start\": 1680113145.1458833, \"end\": 1680113153.9157445}}","success":true,"duration_us":8916228},"function_output":{"body":{"cold":true,"start":1680113145.145883,"end":1680113153.9157443,"latency":8.769861221313477}},"client_latency_us":11039783,"function_name":"video_processing-0","function_version":"0.0.1","tid":"11be0c51tof3fbto0c58to50fdtoebee0f710288","invoke_start":"2023-03-29 14:05:42.87749613"},{"worker_response":{"json_result":"{\"body\": {\"network\": 4.497120380401611, \"serialization\": 4.497121095657349, \"latency\": 4.497121334075928, \"cold\": true, \"start\": 1680113149.6639173, \"end\": 1680113154.1610386, \"url\": \"http://v-020.victor.futuresystems.org:8080/1G_file.log\"}}","success":true,"duration_us":4549558},"function_output":{"body":{"cold":true,"start":1680113149.6639173,"end":1680113154.1610386,"latency":4.497121334075928}},"client_latency_us":5132755,"function_name":"fetch_1gfile-0","function_version":"0.0.1","tid":"0e20db81to8fa1tod575toa419tod55c50f2de05","invoke_start":"2023-03-29 14:05:49.029617664"},{"worker_response":{"json_result":"{\"body\": {\"result\": \"2122317824 bytes (2024.0 MBs), 5.9678356647491455 s, 339.1514300494864 MB/s\", \"latency\": 5.9678356647491455, \"cold\": true, \"start\": 1680113150.4781716, \"end\": 1680113156.4460073}}","success":true,"duration_us":6045391},"function_output":{"body":{"cold":true,"start":1680113150.4781716,"end":1680113156.4460073,"latency":5.9678356647491455}},"client_latency_us":6545002,"function_name":"dd-0","function_version":"0.0.1","tid":"7dab2211to79aato1ae3to22a5tocba12bed03ce","invoke_start":"2023-03-29 14:05:49.937453575"},{"worker_response":{"json_result":"{\"body\": {\"latency\": 7.912799835205078, \"cold\": true, \"start\": 1680113152.9850328, \"end\": 1680113160.8978326}}","success":true,"duration_us":8066090},"function_output":{"body":{"cold":true,"start":1680113152.9850328,"end":1680113160.8978326,"latency":7.912799835205078}},"client_latency_us":9162517,"function_name":"video_processing-0","function_version":"0.0.1","tid":"fff60499to3b69to1a2eto8567tod86fe701d42d","invoke_start":"2023-03-29 14:05:51.736512311"},{"worker_response":{"json_result":"{\"body\": {\"result\": \"2122317824 bytes (2024.0 MBs), 4.567540407180786 s, 443.1268953456877 MB/s\", \"latency\": 4.567540407180786, \"cold\": false, \"start\": 1680113160.9253268, \"end\": 1680113165.4928672}}","success":true,"duration_us":4628621},"function_output":{"body":{"cold":false,"start":1680113160.9253268,"end":1680113165.4928672,"latency":4.567540407180786}},"client_latency_us":4629881,"function_name":"dd-0","function_version":"0.0.1","tid":"44db1e8cto56d0to163etofb11to6f58a983d3c3","invoke_start":"2023-03-29 14:06:00.887584319"},{"worker_response":{"json_result":"{\"body\": {\"latency\": 7.194725513458252, \"cold\": false, \"start\": 1680113162.0513384, \"end\": 1680113169.246064}}","success":true,"duration_us":7196744},"function_output":{"body":{"cold":false,"start":1680113162.0513384,"end":1680113169.246064,"latency":7.194725513458252}},"client_latency_us":7198064,"function_name":"video_processing-0","function_version":"0.0.1","tid":"940cef9atod657to05a4to254ctodb77c04bc11c","invoke_start":"2023-03-29 14:06:02.049462476"},{"worker_response":{"json_result":"{\"body\": {\"latency\": 7.27946138381958, \"cold\": false, \"start\": 1680113163.7725537, \"end\": 1680113171.052015}}","success":true,"duration_us":7280510},"function_output":{"body":{"cold":false,"start":1680113163.7725537,"end":1680113171.052015,"latency":7.27946138381958}},"client_latency_us":7281745,"function_name":"video_processing-0","function_version":"0.0.1","tid":"7f0393dcto82b7to81d1toce7etoa0f92730c532","invoke_start":"2023-03-29 14:06:03.771474972"},{"worker_response":{"json_result":"{\"body\": {\"result\": \"2122317824 bytes (2024.0 MBs), 4.699775457382202 s, 430.6588726107732 MB/s\", \"latency\": 4.699775457382202, \"cold\": true, \"start\": 1680113165.1283715, \"end\": 1680113169.828147}}","success":true,"duration_us":4823426},"function_output":{"body":{"cold":true,"start":1680113165.1283717,"end":1680113169.828147,"latency":4.699775457382202}},"client_latency_us":5125901,"function_name":"dd-0","function_version":"0.0.1","tid":"eeeaf551to0589tof4e9tod401toe69f9436f5bb","invoke_start":"2023-03-29 14:06:04.770465928"},{"worker_response":{"json_result":"{\"body\": {\"latency\": 7.6102540493011475, \"cold\": true, \"start\": 1680113169.2609298, \"end\": 1680113176.8711839}}","success":true,"duration_us":7783257},"function_output":{"body":{"cold":true,"start":1680113169.2609298,"end":1680113176.871184,"latency":7.6102540493011475}},"client_latency_us":8036706,"function_name":"video_processing-0","function_version":"0.0.1","tid":"27ce47e8toe8deto2b89to6875toa3acefbed6a8","invoke_start":"2023-03-29 14:06:08.835585815"},{"worker_response":{"json_result":"{\"body\": {\"latency\": 7.7436463832855225, \"cold\": false, \"start\": 1680113169.6286428, \"end\": 1680113177.3722892}}","success":true,"duration_us":7744623},"function_output":{"body":{"cold":false,"start":1680113169.6286428,"end":1680113177.3722892,"latency":7.743646383285523}},"client_latency_us":7745811,"function_name":"video_processing-0","function_version":"0.0.1","tid":"2f0f8815to4527to539btoa280to4fb0866e3f4c","invoke_start":"2023-03-29 14:06:09.627471485"},{"worker_response":{"json_result":"{\"body\": {\"result\": \"2122317824 bytes (2024.0 MBs), 4.653794288635254 s, 434.9139378469492 MB/s\", \"latency\": 4.653794288635254, \"cold\": false, \"start\": 1680113170.3726106, \"end\": 1680113175.0264049}}","success":true,"duration_us":4714498},"function_output":{"body":{"cold":false,"start":1680113170.3726106,"end":1680113175.0264049,"latency":4.653794288635254}},"client_latency_us":4715942,"function_name":"dd-0","function_version":"0.0.1","tid":"a23c8b71tob0acto67adto4de2to529f2d7c9d8b","invoke_start":"2023-03-29 14:06:10.336452696"},{"worker_response":{"json_result":"{\"body\": {\"latency\": 7.477133512496948, \"cold\": false, \"start\": 1680113174.986797, \"end\": 1680113182.4639306}}","success":true,"duration_us":7478076},"function_output":{"body":{"cold":false,"start":1680113174.986797,"end":1680113182.4639306,"latency":7.477133512496948}},"client_latency_us":7479340,"function_name":"video_processing-0","function_version":"0.0.1","tid":"333777d6tod4e8to08e5to5335to888d05633ce5","invoke_start":"2023-03-29 14:06:14.985581413"},{"worker_response":{"json_result":"{\"body\": {\"latency\": 7.2694220542907715, \"cold\": false, \"start\": 1680113182.2126884, \"end\": 1680113189.4821105}}","success":true,"duration_us":7270217},"function_output":{"body":{"cold":false,"start":1680113182.2126884,"end":1680113189.4821105,"latency":7.2694220542907715}},"client_latency_us":7271492,"function_name":"video_processing-0","function_version":"0.0.1","tid":"80abcd71to04a0to5751to28dbto0148173ad2d5","invoke_start":"2023-03-29 14:06:22.211587997"},{"worker_response":{"json_result":"{\"body\": {\"latency\": 9.140294551849365, \"cold\": false, \"start\": 1680113187.0675426, \"end\": 1680113196.207837}}","success":true,"duration_us":9141230},"function_output":{"body":{"cold":false,"start":1680113187.0675426,"end":1680113196.207837,"latency":9.140294551849363}},"client_latency_us":9142477,"function_name":"video_processing-0","function_version":"0.0.1","tid":"ba4d9ae3to1b4cto045cto9438tob0b486da7bdc","invoke_start":"2023-03-29 14:06:27.066472709"},{"worker_response":{"json_result":"{\"body\": {\"result\": \"2122317824 bytes (2024.0 MBs), 4.721709251403809 s, 428.65832948063155 MB/s\", \"latency\": 4.721709251403809, \"cold\": false, \"start\": 1680113187.577516, \"end\": 1680113192.2992253}}","success":true,"duration_us":4801254},"function_output":{"body":{"cold":false,"start":1680113187.577516,"end":1680113192.299225,"latency":4.721709251403809}},"client_latency_us":4802452,"function_name":"dd-0","function_version":"0.0.1","tid":"c6aacf6cto577dto8874to43ebtoe33f121b589f","invoke_start":"2023-03-29 14:06:27.548448745"},{"worker_response":{"json_result":"{\"body\": {\"result\": \"2122317824 bytes (2024.0 MBs), 4.55932879447937 s, 443.9249923038552 MB/s\", \"latency\": 4.55932879447937, \"cold\": false, \"start\": 1680113190.4248, \"end\": 1680113194.9841287}}","success":true,"duration_us":4618854},"function_output":{"body":{"cold":false,"start":1680113190.4248,"end":1680113194.9841287,"latency":4.55932879447937}},"client_latency_us":4620324,"function_name":"dd-0","function_version":"0.0.1","tid":"652e95a6to13d8toe4c8toe6adto5b8384bbfa78","invoke_start":"2023-03-29 14:06:30.404457526"},{"worker_response":{"json_result":"{\"body\": {\"result\": \"2122317824 bytes (2024.0 MBs), 4.5936338901519775 s, 440.6097761380451 MB/s\", \"latency\": 4.5936338901519775, \"cold\": false, \"start\": 1680113192.857758, \"end\": 1680113197.451392}}","success":true,"duration_us":4635279},"function_output":{"body":{"cold":false,"start":1680113192.857758,"end":1680113197.451392,"latency":4.5936338901519775}},"client_latency_us":4636545,"function_name":"dd-0","function_version":"0.0.1","tid":"ab164523to87e5tod91ftof20bto59f002819c70","invoke_start":"2023-03-29 14:06:32.838466082"},{"worker_response":{"json_result":"{\"body\": {\"latency\": 12.760161399841309, \"cold\": false, \"start\": 1680113205.0066357, \"end\": 1680113217.766797}}","success":true,"duration_us":12761136},"function_output":{"body":{"cold":false,"start":1680113205.0066357,"end":1680113217.766797,"latency":12.760161399841309}},"client_latency_us":12762372,"function_name":"video_processing-0","function_version":"0.0.1","tid":"ac22dd32to4e58tocf51to7651to80002710a4e4","invoke_start":"2023-03-29 14:06:45.005498071"},{"worker_response":{"json_result":"{\"body\": {\"latency\": 11.398932218551636, \"cold\": false, \"start\": 1680113205.8936145, \"end\": 1680113217.2925467}}","success":true,"duration_us":11400024},"function_output":{"body":{"cold":false,"start":1680113205.8936143,"end":1680113217.2925467,"latency":11.398932218551636}},"client_latency_us":11401176,"function_name":"video_processing-0","function_version":"0.0.1","tid":"3fd7535ctofa27tob4eftoee6btoa75d70259a9b","invoke_start":"2023-03-29 14:06:45.892465132"},{"worker_response":{"json_result":"{\"body\": {\"network\": 4.546361684799194, \"serialization\": 4.546361923217773, \"latency\": 4.54636287689209, \"cold\": false, \"start\": 1680113207.051304, \"end\": 1680113211.597667, \"url\": \"http://v-020.victor.futuresystems.org:8080/1G_file.log\"}}","success":true,"duration_us":4549283},"function_output":{"body":{"cold":false,"start":1680113207.051304,"end":1680113211.597667,"latency":4.54636287689209}},"client_latency_us":4550482,"function_name":"fetch_1gfile-0","function_version":"0.0.1","tid":"55fc752ftob533to75f4to4352toc0698bdd69e1","invoke_start":"2023-03-29 14:06:47.049477057"},{"worker_response":{"json_result":"{\"body\": {\"latency\": 11.839082479476929, \"cold\": false, \"start\": 1680113207.9082246, \"end\": 1680113219.747307}}","success":true,"duration_us":11840330},"function_output":{"body":{"cold":false,"start":1680113207.9082246,"end":1680113219.747307,"latency":11.839082479476929}},"client_latency_us":11882927,"function_name":"video_processing-0","function_version":"0.0.1","tid":"e0a82e1ato8948to93a7tocd88to047f5539ba10","invoke_start":"2023-03-29 14:06:47.865550366"},{"worker_response":{"json_result":"{\"body\": {\"result\": \"2122317824 bytes (2024.0 MBs), 4.670317888259888 s, 433.3752109439646 MB/s\", \"latency\": 4.670317888259888, \"cold\": false, \"start\": 1680113211.7884665, \"end\": 1680113216.4587843}}","success":true,"duration_us":4753150},"function_output":{"body":{"cold":false,"start":1680113211.7884665,"end":1680113216.4587843,"latency":4.670317888259888}},"client_latency_us":4754273,"function_name":"dd-0","function_version":"0.0.1","tid":"46afbd36to7d9dto2832to79e9tofaab2a13f646","invoke_start":"2023-03-29 14:06:51.760451233"},{"worker_response":{"json_result":"{\"body\": {\"latency\": 8.69208550453186, \"cold\": true, \"start\": 1680113213.0993292, \"end\": 1680113221.7914147}}","success":true,"duration_us":9487737},"function_output":{"body":{"cold":true,"start":1680113213.0993292,"end":1680113221.7914147,"latency":8.69208550453186}},"client_latency_us":9661137,"function_name":"video_processing-0","function_version":"0.0.1","tid":"4fa9fb2atob4d3to9572to609eto18139f397533","invoke_start":"2023-03-29 14:06:52.131478595"},{"worker_response":{"json_result":"{\"body\": {\"result\": \"2122317824 bytes (2024.0 MBs), 4.7674479484558105 s, 424.54579932132856 MB/s\", \"latency\": 4.7674479484558105, \"cold\": false, \"start\": 1680113215.7604868, \"end\": 1680113220.5279348}}","success":true,"duration_us":4860119},"function_output":{"body":{"cold":false,"start":1680113215.7604868,"end":1680113220.5279348,"latency":4.7674479484558105}},"client_latency_us":4861509,"function_name":"dd-0","function_version":"0.0.1","tid":"36e5e955todab6to30dato3533to4d532856553d","invoke_start":"2023-03-29 14:06:55.737470133"},{"worker_response":{"json_result":"{\"body\": {\"latency\": 6.546010971069336, \"cold\": false, \"start\": 1680113217.5544956, \"end\": 1680113224.1005065}}","success":true,"duration_us":6546878},"function_output":{"body":{"cold":false,"start":1680113217.5544956,"end":1680113224.1005063,"latency":6.546010971069336}},"client_latency_us":6548031,"function_name":"video_processing-0","function_version":"0.0.1","tid":"9330fc95to2b84to76e3to0ceeto15b1396c0811","invoke_start":"2023-03-29 14:06:57.553465651"},{"worker_response":{"json_result":"{\"body\": {\"result\": \"2122317824 bytes (2024.0 MBs), 4.627394437789917 s, 437.3951750192014 MB/s\", \"latency\": 4.627394437789917, \"cold\": false, \"start\": 1680113219.449798, \"end\": 1680113224.0771925}}","success":true,"duration_us":4685469},"function_output":{"body":{"cold":false,"start":1680113219.449798,"end":1680113224.0771923,"latency":4.627394437789917}},"client_latency_us":4686858,"function_name":"dd-0","function_version":"0.0.1","tid":"7bc25fd1tof443to0674tod820to610f44a47660","invoke_start":"2023-03-29 14:06:59.427467844"},{"worker_response":{"json_result":"{\"body\": {\"result\": \"2122317824 bytes (2024.0 MBs), 4.602120399475098 s, 439.7972726291234 MB/s\", \"latency\": 4.602120399475098, \"cold\": false, \"start\": 1680113222.95263, \"end\": 1680113227.5547504}}","success":true,"duration_us":4657702},"function_output":{"body":{"cold":false,"start":1680113222.95263,"end":1680113227.5547504,"latency":4.602120399475098}},"client_latency_us":4659267,"function_name":"dd-0","function_version":"0.0.1","tid":"16f1652bto561ctoe725to343atoc927c18c6149","invoke_start":"2023-03-29 14:07:02.928453353"},{"worker_response":{"json_result":"{\"body\": {\"result\": \"2122317824 bytes (2024.0 MBs), 4.5498740673065186 s, 444.8474771079078 MB/s\", \"latency\": 4.5498740673065186, \"cold\": false, \"start\": 1680113225.601386, \"end\": 1680113230.1512601}}","success":true,"duration_us":4590098},"function_output":{"body":{"cold":false,"start":1680113225.601386,"end":1680113230.15126,"latency":4.5498740673065186}},"client_latency_us":4591378,"function_name":"dd-0","function_version":"0.0.1","tid":"c632aaf0to8a7eto1591tod1c2to33edf41e3198","invoke_start":"2023-03-29 14:07:05.582470123"},{"worker_response":{"json_result":"{\"body\": {\"latency\": 6.3098671436309814, \"cold\": false, \"start\": 1680113227.8435292, \"end\": 1680113234.1533964}}","success":true,"duration_us":6310626},"function_output":{"body":{"cold":false,"start":1680113227.8435292,"end":1680113234.1533964,"latency":6.3098671436309814}},"client_latency_us":6311939,"function_name":"video_processing-0","function_version":"0.0.1","tid":"085b922etoe9d4to8ac5to2dbato85e278534210","invoke_start":"2023-03-29 14:07:07.842491908"},{"worker_response":{"json_result":"{\"body\": {\"result\": \"2122317824 bytes (2024.0 MBs), 4.6896445751190186 s, 431.58921056370946 MB/s\", \"latency\": 4.6896445751190186, \"cold\": false, \"start\": 1680113229.902487, \"end\": 1680113234.5921316}}","success":true,"duration_us":4734373},"function_output":{"body":{"cold":false,"start":1680113229.902487,"end":1680113234.5921316,"latency":4.6896445751190186}},"client_latency_us":4735598,"function_name":"dd-0","function_version":"0.0.1","tid":"bd12ea16to7459to7088toae3ctoaf6307d2b048","invoke_start":"2023-03-29 14:07:09.883490323"},{"worker_response":{"json_result":"{\"body\": {\"network\": 4.48305344581604, \"serialization\": 4.4830543994903564, \"latency\": 4.4830543994903564, \"cold\": false, \"start\": 1680113233.5725079, \"end\": 1680113238.0555623, \"url\": \"http://v-020.victor.futuresystems.org:8080/1G_file.log\"}}","success":true,"duration_us":4485158},"function_output":{"body":{"cold":false,"start":1680113233.572508,"end":1680113238.0555625,"latency":4.4830543994903564}},"client_latency_us":4486312,"function_name":"fetch_1gfile-0","function_version":"0.0.1","tid":"bf85fbb4toff75to53f9tocab2tob08e5776279a","invoke_start":"2023-03-29 14:07:13.571468829"},{"worker_response":{"json_result":"{\"body\": {\"latency\": 6.969104051589966, \"cold\": false, \"start\": 1680113235.6228888, \"end\": 1680113242.5919929}}","success":true,"duration_us":6969859},"function_output":{"body":{"cold":false,"start":1680113235.6228888,"end":1680113242.5919929,"latency":6.969104051589966}},"client_latency_us":7027517,"function_name":"video_processing-0","function_version":"0.0.1","tid":"3dfddee9to3634tof11bto988fto307c8ffecbc8","invoke_start":"2023-03-29 14:07:15.565454859"},{"worker_response":{"json_result":"{\"body\": {\"result\": \"2122317824 bytes (2024.0 MBs), 4.608297109603882 s, 439.2077923495645 MB/s\", \"latency\": 4.608297109603882, \"cold\": false, \"start\": 1680113237.8317425, \"end\": 1680113242.4400396}}","success":true,"duration_us":4728818},"function_output":{"body":{"cold":false,"start":1680113237.8317423,"end":1680113242.4400396,"latency":4.608297109603882}},"client_latency_us":4778298,"function_name":"dd-0","function_version":"0.0.1","tid":"6d092437to116fto2396to84b4to6a9f85a8e1c0","invoke_start":"2023-03-29 14:07:17.706469269"},{"worker_response":{"json_result":"{\"body\": {\"result\": \"2122317824 bytes (2024.0 MBs), 4.620511531829834 s, 438.046737045681 MB/s\", \"latency\": 4.620511531829834, \"cold\": false, \"start\": 1680113249.0497427, \"end\": 1680113253.6702542}}","success":true,"duration_us":4672113},"function_output":{"body":{"cold":false,"start":1680113249.0497427,"end":1680113253.6702542,"latency":4.620511531829834}},"client_latency_us":4673437,"function_name":"dd-0","function_version":"0.0.1","tid":"aeb4c71ctof0f8toe5acto37c0to284cfd71b6be","invoke_start":"2023-03-29 14:07:29.02248813"},{"worker_response":{"json_result":"{\"body\": {\"latency\": 6.213918209075928, \"cold\": false, \"start\": 1680113252.0926623, \"end\": 1680113258.3065805}}","success":true,"duration_us":6214754},"function_output":{"body":{"cold":false,"start":1680113252.0926623,"end":1680113258.3065803,"latency":6.213918209075928}},"client_latency_us":6215948,"function_name":"video_processing-0","function_version":"0.0.1","tid":"0a092c84to64a5to8cd4toe836to364be0c8295e","invoke_start":"2023-03-29 14:07:32.0915772"},{"worker_response":{"json_result":"{\"body\": {\"network\": 5.202651023864746, \"serialization\": 5.202651739120483, \"latency\": 5.2026519775390625, \"cold\": false, \"start\": 1680113257.9065118, \"end\": 1680113263.1091638, \"url\": \"http://v-020.victor.futuresystems.org:8080/1G_file.log\"}}","success":true,"duration_us":5204050},"function_output":{"body":{"cold":false,"start":1680113257.9065118,"end":1680113263.1091638,"latency":5.2026519775390625}},"client_latency_us":5205195,"function_name":"fetch_1gfile-0","function_version":"0.0.1","tid":"6e49097btod967toe8d7toc410to463f2234bdc6","invoke_start":"2023-03-29 14:07:37.905473485"},{"worker_response":{"json_result":"{\"body\": {\"network\": 10.232635259628296, \"serialization\": 10.232636451721191, \"latency\": 10.23263669013977, \"cold\": true, \"start\": 1680113259.7896647, \"end\": 1680113270.0223014, \"url\": \"http://v-020.victor.futuresystems.org:8080/1G_file.log\"}}","success":true,"duration_us":10291264},"function_output":{"body":{"cold":true,"start":1680113259.7896647,"end":1680113270.0223014,"latency":10.23263669013977}},"client_latency_us":10613715,"function_name":"fetch_1gfile-0","function_version":"0.0.1","tid":"02d4f4b1to81d2toea28to67c4tod1784947db4b","invoke_start":"2023-03-29 14:07:39.41039746"},{"worker_response":{"json_result":"{\"body\": {\"result\": \"2122317824 bytes (2024.0 MBs), 4.5572333335876465 s, 444.1291133992961 MB/s\", \"latency\": 4.5572333335876465, \"cold\": false, \"start\": 1680113261.081356, \"end\": 1680113265.6385894}}","success":true,"duration_us":4629512},"function_output":{"body":{"cold":false,"start":1680113261.081356,"end":1680113265.6385894,"latency":4.5572333335876465}},"client_latency_us":4688654,"function_name":"dd-0","function_version":"0.0.1","tid":"6954b58dto6585to43e1toc70ctof51bb3c1ab20","invoke_start":"2023-03-29 14:07:40.995479479"},{"worker_response":{"json_result":"{\"body\": {\"latency\": 8.071945428848267, \"cold\": false, \"start\": 1680113262.4104533, \"end\": 1680113270.4823987}}","success":true,"duration_us":8072780},"function_output":{"body":{"cold":false,"start":1680113262.410453,"end":1680113270.4823987,"latency":8.071945428848267}},"client_latency_us":8137866,"function_name":"video_processing-0","function_version":"0.0.1","tid":"a4a9a885to82c5toe448to3465to0002d9306531","invoke_start":"2023-03-29 14:07:42.345466628"},{"worker_response":{"json_result":"{\"body\": {\"network\": 6.310142755508423, \"serialization\": 6.310143232345581, \"latency\": 6.31014347076416, \"cold\": false, \"start\": 1680113265.0813594, \"end\": 1680113271.3915029, \"url\": \"http://v-020.victor.futuresystems.org:8080/1G_file.log\"}}","success":true,"duration_us":6311763},"function_output":{"body":{"cold":false,"start":1680113265.0813594,"end":1680113271.3915029,"latency":6.31014347076416}},"client_latency_us":6335768,"function_name":"fetch_1gfile-0","function_version":"0.0.1","tid":"89bdd1bbto1505to3c1bto0d9fto187f8f70f6c9","invoke_start":"2023-03-29 14:07:45.057471511"},{"worker_response":{"json_result":"{\"body\": {\"network\": 4.485447883605957, \"serialization\": 4.485449552536011, \"latency\": 4.485449552536011, \"cold\": false, \"start\": 1680113275.0551145, \"end\": 1680113279.540564, \"url\": \"http://v-020.victor.futuresystems.org:8080/1G_file.log\"}}","success":true,"duration_us":4487348},"function_output":{"body":{"cold":false,"start":1680113275.0551145,"end":1680113279.540564,"latency":4.485449552536011}},"client_latency_us":4488594,"function_name":"fetch_1gfile-0","function_version":"0.0.1","tid":"0b4551f2todf0etoec68to8fcbtod4f826065c29","invoke_start":"2023-03-29 14:07:55.053472741"},{"worker_response":{"json_result":"{\"body\": {\"latency\": 6.955659627914429, \"cold\": false, \"start\": 1680113277.0012822, \"end\": 1680113283.9569418}}","success":true,"duration_us":6956467},"function_output":{"body":{"cold":false,"start":1680113277.0012822,"end":1680113283.9569418,"latency":6.955659627914429}},"client_latency_us":7013563,"function_name":"video_processing-0","function_version":"0.0.1","tid":"272b5868to17a4tobc62to6e55tob706cb008f87","invoke_start":"2023-03-29 14:07:56.944420596"},{"worker_response":{"json_result":"{\"body\": {\"latency\": 6.522396087646484, \"cold\": false, \"start\": 1680113280.166935, \"end\": 1680113286.689331}}","success":true,"duration_us":6523666},"function_output":{"body":{"cold":false,"start":1680113280.166935,"end":1680113286.689331,"latency":6.522396087646484}},"client_latency_us":6524814,"function_name":"video_processing-0","function_version":"0.0.1","tid":"40667b74toce3eto00a3to49afto48c19fa5cc9e","invoke_start":"2023-03-29 14:08:00.165583416"},{"worker_response":{"json_result":"{\"body\": {\"latency\": 6.780784368515015, \"cold\": false, \"start\": 1680113281.5344439, \"end\": 1680113288.3152282}}","success":true,"duration_us":6781638},"function_output":{"body":{"cold":false,"start":1680113281.534444,"end":1680113288.3152282,"latency":6.780784368515015}},"client_latency_us":6782745,"function_name":"video_processing-0","function_version":"0.0.1","tid":"6c509ff3to9ad1toa9f8tobeb3toe7bcf31daf90","invoke_start":"2023-03-29 14:08:01.533487762"},{"worker_response":{"json_result":"{\"body\": {\"latency\": 10.16960072517395, \"cold\": false, \"start\": 1680113283.0985892, \"end\": 1680113293.26819}}","success":true,"duration_us":10170494},"function_output":{"body":{"cold":false,"start":1680113283.0985892,"end":1680113293.26819,"latency":10.16960072517395}},"client_latency_us":10171752,"function_name":"video_processing-0","function_version":"0.0.1","tid":"a5754769to97c0to8ad6to513fto16b3c2c8bf4c","invoke_start":"2023-03-29 14:08:03.097502637"},{"worker_response":{"json_result":"{\"body\": {\"result\": \"2122317824 bytes (2024.0 MBs), 4.6786205768585205 s, 432.6061425051534 MB/s\", \"latency\": 4.6786205768585205, \"cold\": false, \"start\": 1680113286.5657878, \"end\": 1680113291.2444084}}","success":true,"duration_us":4737986},"function_output":{"body":{"cold":false,"start":1680113286.5657878,"end":1680113291.2444084,"latency":4.6786205768585205}},"client_latency_us":4739291,"function_name":"dd-0","function_version":"0.0.1","tid":"0ca3ea58toba75to058btod4c2to3d4525be0112","invoke_start":"2023-03-29 14:08:06.535479498"},{"worker_response":{"json_result":"{\"body\": {\"result\": \"2122317824 bytes (2024.0 MBs), 4.540484428405762 s, 445.76741356883355 MB/s\", \"latency\": 4.540484428405762, \"cold\": false, \"start\": 1680113297.410852, \"end\": 1680113301.9513364}}","success":true,"duration_us":4659618},"function_output":{"body":{"cold":false,"start":1680113297.410852,"end":1680113301.9513364,"latency":4.540484428405762}},"client_latency_us":4660793,"function_name":"dd-0","function_version":"0.0.1","tid":"36336626toebe4to1814to2af7to9aed9c29abbc","invoke_start":"2023-03-29 14:08:17.321470999"},{"worker_response":{"json_result":"{\"body\": {\"latency\": 9.006573915481567, \"cold\": false, \"start\": 1680113298.229403, \"end\": 1680113307.235977}}","success":true,"duration_us":9007512},"function_output":{"body":{"cold":false,"start":1680113298.229403,"end":1680113307.235977,"latency":9.006573915481567}},"client_latency_us":9008745,"function_name":"video_processing-0","function_version":"0.0.1","tid":"1958d84cto5fb2toda54to4ccfto2caadc05fa7c","invoke_start":"2023-03-29 14:08:18.228452503"},{"worker_response":{"json_result":"{\"body\": {\"latency\": 8.690914630889893, \"cold\": false, \"start\": 1680113298.7623937, \"end\": 1680113307.4533083}}","success":true,"duration_us":8691829},"function_output":{"body":{"cold":false,"start":1680113298.7623937,"end":1680113307.4533083,"latency":8.690914630889893}},"client_latency_us":8692887,"function_name":"video_processing-0","function_version":"0.0.1","tid":"f2380b41tob9datoa990tocd21to4d2547e0895a","invoke_start":"2023-03-29 14:08:18.761444307"},{"worker_response":{"json_result":"{\"body\": {\"result\": \"2122317824 bytes (2024.0 MBs), 4.6529786586761475 s, 434.99017478319206 MB/s\", \"latency\": 4.6529786586761475, \"cold\": false, \"start\": 1680113303.586888, \"end\": 1680113308.2398667}}","success":true,"duration_us":4711797},"function_output":{"body":{"cold":false,"start":1680113303.586888,"end":1680113308.2398667,"latency":4.6529786586761475}},"client_latency_us":4713031,"function_name":"dd-0","function_version":"0.0.1","tid":"806e5321to589eto318dto901ftoc3435a562162","invoke_start":"2023-03-29 14:08:23.5514589"},{"worker_response":{"json_result":"{\"body\": {\"network\": 4.467854976654053, \"serialization\": 4.467855930328369, \"latency\": 4.467856168746948, \"cold\": false, \"start\": 1680113312.4615138, \"end\": 1680113316.92937, \"url\": \"http://v-020.victor.futuresystems.org:8080/1G_file.log\"}}","success":true,"duration_us":4469215},"function_output":{"body":{"cold":false,"start":1680113312.4615138,"end":1680113316.92937,"latency":4.467856168746948}},"client_latency_us":4470561,"function_name":"fetch_1gfile-0","function_version":"0.0.1","tid":"7f968910to3aaftoe6aato7a20tob0e0cbd73cb7","invoke_start":"2023-03-29 14:08:32.460473471"},{"worker_response":{"json_result":"{\"body\": {\"network\": 4.470617294311523, \"serialization\": 4.470617771148682, \"latency\": 4.470618009567261, \"cold\": false, \"start\": 1680113317.6914556, \"end\": 1680113322.1620736, \"url\": \"http://v-020.victor.futuresystems.org:8080/1G_file.log\"}}","success":true,"duration_us":4471836},"function_output":{"body":{"cold":false,"start":1680113317.6914556,"end":1680113322.1620736,"latency":4.470618009567261}},"client_latency_us":4473017,"function_name":"fetch_1gfile-0","function_version":"0.0.1","tid":"a699544ctoc61atoa018tocd34tod9d337435186","invoke_start":"2023-03-29 14:08:37.690472289"},{"worker_response":{"json_result":"{\"body\": {\"latency\": 7.8799707889556885, \"cold\": false, \"start\": 1680113320.4132292, \"end\": 1680113328.2932}}","success":true,"duration_us":7880806},"function_output":{"body":{"cold":false,"start":1680113320.4132292,"end":1680113328.2932,"latency":7.879970788955688}},"client_latency_us":7943631,"function_name":"video_processing-0","function_version":"0.0.1","tid":"45230700tod19cto28d4tof2b6to3dc1cb4ec5b0","invoke_start":"2023-03-29 14:08:40.350569638"},{"worker_response":{"json_result":"{\"body\": {\"latency\": 7.550797939300537, \"cold\": false, \"start\": 1680113321.5122294, \"end\": 1680113329.0630274}}","success":true,"duration_us":7551668},"function_output":{"body":{"cold":false,"start":1680113321.5122294,"end":1680113329.0630274,"latency":7.550797939300537}},"client_latency_us":7621661,"function_name":"video_processing-0","function_version":"0.0.1","tid":"2f52b945to400bto6163to2a18to43fdb3391b48","invoke_start":"2023-03-29 14:08:41.442504904"},{"worker_response":{"json_result":"{\"body\": {\"network\": 4.594051837921143, \"serialization\": 4.594052791595459, \"latency\": 4.594053030014038, \"cold\": false, \"start\": 1680113323.7605598, \"end\": 1680113328.3546128, \"url\": \"http://v-020.victor.futuresystems.org:8080/1G_file.log\"}}","success":true,"duration_us":4595477},"function_output":{"body":{"cold":false,"start":1680113323.7605598,"end":1680113328.3546128,"latency":4.594053030014038}},"client_latency_us":4596719,"function_name":"fetch_1gfile-0","function_version":"0.0.1","tid":"8f0386c2toa8c9to758btobdd0to9b7bf5f6cb60","invoke_start":"2023-03-29 14:08:43.759476708"},{"worker_response":{"json_result":"{\"body\": {\"result\": \"2122317824 bytes (2024.0 MBs), 4.714222431182861 s, 429.3390966476207 MB/s\", \"latency\": 4.714222431182861, \"cold\": false, \"start\": 1680113326.0250022, \"end\": 1680113330.7392247}}","success":true,"duration_us":4794115},"function_output":{"body":{"cold":false,"start":1680113326.0250022,"end":1680113330.739225,"latency":4.714222431182861}},"client_latency_us":4852240,"function_name":"dd-0","function_version":"0.0.1","tid":"29d7145eto7a5etoc19dtobffato266c72a71814","invoke_start":"2023-03-29 14:08:45.94138951"},{"worker_response":{"json_result":"{\"body\": {\"result\": \"2122317824 bytes (2024.0 MBs), 4.736079692840576 s, 427.3576737020778 MB/s\", \"latency\": 4.736079692840576, \"cold\": false, \"start\": 1680113326.4094586, \"end\": 1680113331.1455383}}","success":true,"duration_us":4796296},"function_output":{"body":{"cold":false,"start":1680113326.4094586,"end":1680113331.1455383,"latency":4.736079692840576}},"client_latency_us":4854676,"function_name":"dd-0","function_version":"0.0.1","tid":"c2bd2c08tocfbftoe5b8tob52eto80519b8808d0","invoke_start":"2023-03-29 14:08:46.322482498"},{"worker_response":{"json_result":"{\"body\": {\"result\": \"2122317824 bytes (2024.0 MBs), 4.581722974777222 s, 441.75521111649346 MB/s\", \"latency\": 4.581722974777222, \"cold\": false, \"start\": 1680113334.7815726, \"end\": 1680113339.3632956}}","success":true,"duration_us":4646312},"function_output":{"body":{"cold":false,"start":1680113334.7815726,"end":1680113339.3632956,"latency":4.581722974777222}},"client_latency_us":4647533,"function_name":"dd-0","function_version":"0.0.1","tid":"12350bc7to6649to382dto5e00to533a64a8def7","invoke_start":"2023-03-29 14:08:54.744472958"},{"worker_response":{"json_result":"{\"body\": {\"network\": 8.505672693252563, \"serialization\": 8.505673170089722, \"latency\": 8.5056734085083, \"cold\": false, \"start\": 1680113336.5023668, \"end\": 1680113345.0080402, \"url\": \"http://v-020.victor.futuresystems.org:8080/1G_file.log\"}}","success":true,"duration_us":8506813},"function_output":{"body":{"cold":false,"start":1680113336.5023668,"end":1680113345.0080402,"latency":8.5056734085083}},"client_latency_us":8508012,"function_name":"fetch_1gfile-0","function_version":"0.0.1","tid":"bb1c846fto0891tob508to285bto177f3c70e19d","invoke_start":"2023-03-29 14:08:56.501461837"},{"worker_response":{"json_result":"{\"body\": {\"network\": 19.088096857070923, \"serialization\": 19.088097095489502, \"latency\": 19.08809733390808, \"cold\": false, \"start\": 1680113336.8281546, \"end\": 1680113355.916252, \"url\": \"http://v-020.victor.futuresystems.org:8080/1G_file.log\"}}","success":true,"duration_us":19089195},"function_output":{"body":{"cold":false,"start":1680113336.8281546,"end":1680113355.916252,"latency":19.08809733390808}},"client_latency_us":19106863,"function_name":"fetch_1gfile-0","function_version":"0.0.1","tid":"20bdb22ato41a1to08f6to2da7to74268f87a12c","invoke_start":"2023-03-29 14:08:56.810442575"},{"worker_response":{"json_result":"{\"body\": {\"network\": 18.525866270065308, \"serialization\": 18.525866746902466, \"latency\": 18.525866985321045, \"cold\": true, \"start\": 1680113337.8092642, \"end\": 1680113356.3351312, \"url\": \"http://v-020.victor.futuresystems.org:8080/1G_file.log\"}}","success":true,"duration_us":18588894},"function_output":{"body":{"cold":true,"start":1680113337.8092642,"end":1680113356.3351312,"latency":18.525866985321045}},"client_latency_us":18864037,"function_name":"fetch_1gfile-0","function_version":"0.0.1","tid":"48a3ae86to8296to3d89tof791tod7b87a7c0890","invoke_start":"2023-03-29 14:08:57.472445563"},{"worker_response":{"json_result":"{\"body\": {\"latency\": 9.490363359451294, \"cold\": false, \"start\": 1680113337.799317, \"end\": 1680113347.2896802}}","success":true,"duration_us":9491209},"function_output":{"body":{"cold":false,"start":1680113337.799317,"end":1680113347.2896802,"latency":9.490363359451294}},"client_latency_us":9563284,"function_name":"video_processing-0","function_version":"0.0.1","tid":"fdc9a519to4d85to1dbcto2609tof00f7aaac091","invoke_start":"2023-03-29 14:08:57.727446963"},{"worker_response":{"json_result":"{\"body\": {\"network\": 36.76818346977234, \"serialization\": 36.768184661865234, \"latency\": 36.768184661865234, \"cold\": true, \"start\": 1680113343.8179145, \"end\": 1680113380.5860991, \"url\": \"http://v-020.victor.futuresystems.org:8080/1G_file.log\"}}","success":true,"duration_us":36822808},"function_output":{"body":{"cold":true,"start":1680113343.8179145,"end":1680113380.5860991,"latency":36.768184661865234}},"client_latency_us":37151268,"function_name":"fetch_1gfile-0","function_version":"0.0.1","tid":"da46948ato3219to7889to078ctod31fb0694e0d","invoke_start":"2023-03-29 14:09:03.436463863"},{"worker_response":{"json_result":"{\"body\": {\"network\": 19.269865036010742, \"serialization\": 19.269866943359375, \"latency\": 19.269867181777954, \"cold\": true, \"start\": 1680113345.0559325, \"end\": 1680113364.3257997, \"url\": \"http://v-020.victor.futuresystems.org:8080/1G_file.log\"}}","success":true,"duration_us":19330625},"function_output":{"body":{"cold":true,"start":1680113345.0559323,"end":1680113364.3257997,"latency":19.26986718177795}},"client_latency_us":19645299,"function_name":"fetch_1gfile-0","function_version":"0.0.1","tid":"3fe76ee0toc57bto6ce8to58e9tofe589b5b039e","invoke_start":"2023-03-29 14:09:04.68245986"},{"worker_response":{"json_result":"{\"body\": {\"result\": \"2122317824 bytes (2024.0 MBs), 4.655777931213379 s, 434.7286382433858 MB/s\", \"latency\": 4.655777931213379, \"cold\": false, \"start\": 1680113345.4326549, \"end\": 1680113350.0884328}}","success":true,"duration_us":4713396},"function_output":{"body":{"cold":false,"start":1680113345.4326549,"end":1680113350.0884328,"latency":4.655777931213379}},"client_latency_us":4772827,"function_name":"dd-0","function_version":"0.0.1","tid":"39d96d9fto1ecftod7c9to91e3to60857c07188b","invoke_start":"2023-03-29 14:09:05.342452637"},{"worker_response":{"json_result":"{\"body\": {\"network\": 32.35944700241089, \"serialization\": 32.359447717666626, \"latency\": 32.359448194503784, \"cold\": false, \"start\": 1680113346.9405608, \"end\": 1680113379.300009, \"url\": \"http://v-020.victor.futuresystems.org:8080/1G_file.log\"}}","success":true,"duration_us":32360440},"function_output":{"body":{"cold":false,"start":1680113346.9405608,"end":1680113379.300009,"latency":32.359448194503784}},"client_latency_us":32424708,"function_name":"fetch_1gfile-0","function_version":"0.0.1","tid":"6ff4e6c9to4eb1to43catof140toe444e1777315","invoke_start":"2023-03-29 14:09:06.876465848"},{"worker_response":{"json_result":"{\"body\": {\"network\": 34.12387180328369, \"serialization\": 34.12387251853943, \"latency\": 34.12387275695801, \"cold\": true, \"start\": 1680113348.6140413, \"end\": 1680113382.737914, \"url\": \"http://v-020.victor.futuresystems.org:8080/1G_file.log\"}}","success":true,"duration_us":34182478},"function_output":{"body":{"cold":true,"start":1680113348.614041,"end":1680113382.737914,"latency":34.12387275695801}},"client_latency_us":34487945,"function_name":"fetch_1gfile-0","function_version":"0.0.1","tid":"665913f6toad5bto7229tod1f9to44324466eb0d","invoke_start":"2023-03-29 14:09:08.25145862"},{"worker_response":{"json_result":"{\"body\": {\"network\": 27.314936876296997, \"serialization\": 27.31493878364563, \"latency\": 27.31493902206421, \"cold\": true, \"start\": 1680113355.55321, \"end\": 1680113382.868149, \"url\": \"http://v-020.victor.futuresystems.org:8080/1G_file.log\"}}","success":true,"duration_us":27364736},"function_output":{"body":{"cold":true,"start":1680113355.55321,"end":1680113382.868149,"latency":27.31493902206421}},"client_latency_us":27667180,"function_name":"fetch_1gfile-0","function_version":"0.0.1","tid":"005d5a99toe665to229bto3747to36d8c1a17d46","invoke_start":"2023-03-29 14:09:15.202473809"},{"worker_response":{"json_result":"{\"body\": {\"network\": 28.34966802597046, \"serialization\": 28.349669218063354, \"latency\": 28.349669456481934, \"cold\": false, \"start\": 1680113357.646171, \"end\": 1680113385.9958405, \"url\": \"http://v-020.victor.futuresystems.org:8080/1G_file.log\"}}","success":true,"duration_us":28350804},"function_output":{"body":{"cold":false,"start":1680113357.646171,"end":1680113385.9958403,"latency":28.349669456481937}},"client_latency_us":28408729,"function_name":"fetch_1gfile-0","function_version":"0.0.1","tid":"f6538388tofc05to37e7to7644toffd7f97488ad","invoke_start":"2023-03-29 14:09:17.588470875"},{"worker_response":{"json_result":"{\"body\": {\"result\": \"2122317824 bytes (2024.0 MBs), 4.659999132156372 s, 434.3348448357784 MB/s\", \"latency\": 4.659999132156372, \"cold\": false, \"start\": 1680113357.8942628, \"end\": 1680113362.554262}}","success":true,"duration_us":4731556},"function_output":{"body":{"cold":false,"start":1680113357.8942628,"end":1680113362.554262,"latency":4.659999132156372}},"client_latency_us":4791593,"function_name":"dd-0","function_version":"0.0.1","tid":"16a60720to2f22toa1fetof5d2tod2b029f30f1e","invoke_start":"2023-03-29 14:09:17.806444898"},{"worker_response":{"json_result":"{\"body\": {\"latency\": 10.448132276535034, \"cold\": false, \"start\": 1680113359.7196763, \"end\": 1680113370.1678085}}","success":true,"duration_us":10448893},"function_output":{"body":{"cold":false,"start":1680113359.7196765,"end":1680113370.1678083,"latency":10.448132276535034}},"client_latency_us":10519407,"function_name":"video_processing-0","function_version":"0.0.1","tid":"c6a55d1bto3deatode90to0464to0ec8b6ff8b17","invoke_start":"2023-03-29 14:09:19.649463328"},{"worker_response":{"json_result":"{\"body\": {\"network\": 28.875002145767212, \"serialization\": 28.8750057220459, \"latency\": 28.875005960464478, \"cold\": false, \"start\": 1680113359.970288, \"end\": 1680113388.845294, \"url\": \"http://v-020.victor.futuresystems.org:8080/1G_file.log\"}}","success":true,"duration_us":28876616},"function_output":{"body":{"cold":false,"start":1680113359.970288,"end":1680113388.845294,"latency":28.87500596046448}},"client_latency_us":28948800,"function_name":"fetch_1gfile-0","function_version":"0.0.1","tid":"f402b660to4c35tob33btoe775tob276770ec23a","invoke_start":"2023-03-29 14:09:19.898443885"},{"worker_response":{"json_result":"{\"body\": {\"latency\": 13.967966556549072, \"cold\": false, \"start\": 1680113361.4018226, \"end\": 1680113375.3697891}}","success":true,"duration_us":13968954},"function_output":{"body":{"cold":false,"start":1680113361.4018226,"end":1680113375.3697891,"latency":13.967966556549072}},"client_latency_us":14036665,"function_name":"video_processing-0","function_version":"0.0.1","tid":"b6f329a6to9667to8ed4to5858to98dd35421031","invoke_start":"2023-03-29 14:09:21.334456544"},{"worker_response":{"json_result":"{\"body\": {\"latency\": 14.71511459350586, \"cold\": false, \"start\": 1680113361.7887726, \"end\": 1680113376.5038872}}","success":true,"duration_us":14715924},"function_output":{"body":{"cold":false,"start":1680113361.7887726,"end":1680113376.5038872,"latency":14.71511459350586}},"client_latency_us":14786476,"function_name":"video_processing-0","function_version":"0.0.1","tid":"c038bc78to79b7to7e67tofd49to189cfcbfe7ee","invoke_start":"2023-03-29 14:09:21.71844687"},{"worker_response":{"json_result":"{\"body\": {\"network\": 24.1591055393219, \"serialization\": 24.159106969833374, \"latency\": 24.159107208251953, \"cold\": true, \"start\": 1680113362.5787907, \"end\": 1680113386.7378979, \"url\": \"http://v-020.victor.futuresystems.org:8080/1G_file.log\"}}","success":true,"duration_us":24202787},"function_output":{"body":{"cold":true,"start":1680113362.578791,"end":1680113386.737898,"latency":24.159107208251953}},"client_latency_us":24522322,"function_name":"fetch_1gfile-0","function_version":"0.0.1","tid":"e3c895c6to8af5toa8f7to174ftoc807b9f01a78","invoke_start":"2023-03-29 14:09:22.217450979"},{"worker_response":{"json_result":"{\"body\": {\"result\": \"2122317824 bytes (2024.0 MBs), 4.640976667404175 s, 436.1150992668271 MB/s\", \"latency\": 4.640976667404175, \"cold\": false, \"start\": 1680113365.071369, \"end\": 1680113369.7123456}}","success":true,"duration_us":4720756},"function_output":{"body":{"cold":false,"start":1680113365.071369,"end":1680113369.7123456,"latency":4.640976667404175}},"client_latency_us":4781972,"function_name":"dd-0","function_version":"0.0.1","tid":"0e595692to9ef2to727etoe336to51c402832a53","invoke_start":"2023-03-29 14:09:24.984488173"},{"worker_response":{"json_result":"{\"body\": {\"network\": 17.810837507247925, \"serialization\": 17.810837984085083, \"latency\": 17.810838222503662, \"cold\": false, \"start\": 1680113372.7520363, \"end\": 1680113390.5628746, \"url\": \"http://v-020.victor.futuresystems.org:8080/1G_file.log\"}}","success":true,"duration_us":17812963},"function_output":{"body":{"cold":false,"start":1680113372.7520363,"end":1680113390.5628746,"latency":17.810838222503662}},"client_latency_us":17886652,"function_name":"fetch_1gfile-0","function_version":"0.0.1","tid":"306a105btoe9e6to6e90to9a67toef30cd620b58","invoke_start":"2023-03-29 14:09:32.678471532"},{"worker_response":{"json_result":"{\"body\": {\"result\": \"2122317824 bytes (2024.0 MBs), 4.535079002380371 s, 446.29873017375076 MB/s\", \"latency\": 4.535079002380371, \"cold\": false, \"start\": 1680113376.8929162, \"end\": 1680113381.4279952}}","success":true,"duration_us":4592430},"function_output":{"body":{"cold":false,"start":1680113376.8929162,"end":1680113381.4279952,"latency":4.535079002380371}},"client_latency_us":4661281,"function_name":"dd-0","function_version":"0.0.1","tid":"bec258cftoc6dbtoad44todd51to0d6e53c988c2","invoke_start":"2023-03-29 14:09:36.79346416"},{"worker_response":{"json_result":"{\"body\": {\"latency\": 9.63127875328064, \"cold\": false, \"start\": 1680113381.1289294, \"end\": 1680113390.7602081}}","success":true,"duration_us":9632277},"function_output":{"body":{"cold":false,"start":1680113381.1289294,"end":1680113390.760208,"latency":9.63127875328064}},"client_latency_us":9697867,"function_name":"video_processing-0","function_version":"0.0.1","tid":"909113e0to547atoac56todcd2to28dc5d697919","invoke_start":"2023-03-29 14:09:41.063469601"},{"worker_response":{"json_result":"{\"body\": {\"latency\": 17.01113796234131, \"cold\": false, \"start\": 1680113384.187274, \"end\": 1680113401.198412}}","success":true,"duration_us":17011961},"function_output":{"body":{"cold":false,"start":1680113384.187274,"end":1680113401.198412,"latency":17.01113796234131}},"client_latency_us":17064096,"function_name":"video_processing-0","function_version":"0.0.1","tid":"059cb308to4e9fto1682toed13to36ed8a2dfaef","invoke_start":"2023-03-29 14:09:44.135472409"},{"worker_response":{"json_result":"{\"body\": {\"result\": \"2122317824 bytes (2024.0 MBs), 4.638001918792725 s, 436.39481730245785 MB/s\", \"latency\": 4.638001918792725, \"cold\": false, \"start\": 1680113385.402852, \"end\": 1680113390.040854}}","success":true,"duration_us":4698063},"function_output":{"body":{"cold":false,"start":1680113385.402852,"end":1680113390.040854,"latency":4.638001918792725}},"client_latency_us":4755227,"function_name":"dd-0","function_version":"0.0.1","tid":"0c4f98a5todc94toc809to4c93to34d8dbbc8740","invoke_start":"2023-03-29 14:09:45.322473689"},{"worker_response":{"json_result":"{\"body\": {\"result\": \"2122317824 bytes (2024.0 MBs), 4.699739217758179 s, 430.66219341537584 MB/s\", \"latency\": 4.699739217758179, \"cold\": false, \"start\": 1680113385.741037, \"end\": 1680113390.440776}}","success":true,"duration_us":4759664},"function_output":{"body":{"cold":false,"start":1680113385.741037,"end":1680113390.440776,"latency":4.699739217758179}},"client_latency_us":4819055,"function_name":"dd-0","function_version":"0.0.1","tid":"ddca07e5to7c3ato8fcdto9fb8tod4d4bfb8c88f","invoke_start":"2023-03-29 14:09:45.652388017"},{"worker_response":{"json_result":"{\"body\": {\"latency\": 8.93949031829834, \"cold\": false, \"start\": 1680113389.9830863, \"end\": 1680113398.9225767}}","success":true,"duration_us":8940282},"function_output":{"body":{"cold":false,"start":1680113389.9830863,"end":1680113398.922577,"latency":8.93949031829834}},"client_latency_us":8978302,"function_name":"video_processing-0","function_version":"0.0.1","tid":"af4d3ce7to081cto4746toe7c5to0f629a619d11","invoke_start":"2023-03-29 14:09:49.945459778"},{"worker_response":{"json_result":"{\"body\": {\"latency\": 12.922757863998413, \"cold\": false, \"start\": 1680113390.5707057, \"end\": 1680113403.4934635}}","success":true,"duration_us":12923933},"function_output":{"body":{"cold":false,"start":1680113390.5707057,"end":1680113403.4934635,"latency":12.922757863998411}},"client_latency_us":12925141,"function_name":"video_processing-0","function_version":"0.0.1","tid":"608693d5to60e8toc14dto654dtoe3fb646ce4f7","invoke_start":"2023-03-29 14:09:50.569448776"},{"worker_response":{"json_result":"{\"body\": {\"network\": 4.548414707183838, \"serialization\": 4.548415184020996, \"latency\": 4.548415422439575, \"cold\": false, \"start\": 1680113390.9323604, \"end\": 1680113395.4807758, \"url\": \"http://v-020.victor.futuresystems.org:8080/1G_file.log\"}}","success":true,"duration_us":4549831},"function_output":{"body":{"cold":false,"start":1680113390.9323604,"end":1680113395.4807758,"latency":4.548415422439575}},"client_latency_us":4550976,"function_name":"fetch_1gfile-0","function_version":"0.0.1","tid":"fd802834to4bc5to5250toe3b7to9d03c7fbd554","invoke_start":"2023-03-29 14:09:50.931448222"},{"worker_response":{"json_result":"{\"body\": {\"result\": \"2122317824 bytes (2024.0 MBs), 4.750797748565674 s, 426.0337120457446 MB/s\", \"latency\": 4.750797748565674, \"cold\": false, \"start\": 1680113397.585527, \"end\": 1680113402.3363247}}","success":true,"duration_us":4898756},"function_output":{"body":{"cold":false,"start":1680113397.585527,"end":1680113402.3363247,"latency":4.750797748565674}},"client_latency_us":4899877,"function_name":"dd-0","function_version":"0.0.1","tid":"904e765eto75adto2aa1to0040to9cede70ad880","invoke_start":"2023-03-29 14:09:57.492471427"},{"worker_response":{"json_result":"{\"body\": {\"result\": \"2122317824 bytes (2024.0 MBs), 4.59744668006897 s, 440.2443662423588 MB/s\", \"latency\": 4.59744668006897, \"cold\": false, \"start\": 1680113401.471991, \"end\": 1680113406.0694377}}","success":true,"duration_us":4693606},"function_output":{"body":{"cold":false,"start":1680113401.471991,"end":1680113406.0694375,"latency":4.59744668006897}},"client_latency_us":4694730,"function_name":"dd-0","function_version":"0.0.1","tid":"3c9d94d6toe308to0cc2to9a76toa425633bc7bc","invoke_start":"2023-03-29 14:10:01.422456193"},{"worker_response":{"json_result":"{\"body\": {\"network\": 4.466543436050415, \"serialization\": 4.466544151306152, \"latency\": 4.4665443897247314, \"cold\": false, \"start\": 1680113405.877359, \"end\": 1680113410.3439033, \"url\": \"http://v-020.victor.futuresystems.org:8080/1G_file.log\"}}","success":true,"duration_us":4467849},"function_output":{"body":{"cold":false,"start":1680113405.877359,"end":1680113410.3439033,"latency":4.4665443897247314}},"client_latency_us":4469026,"function_name":"fetch_1gfile-0","function_version":"0.0.1","tid":"4b4ced52to7adbtoce57to3440to038f980e4bb1","invoke_start":"2023-03-29 14:10:05.876479954"},{"worker_response":{"json_result":"{\"body\": {\"latency\": 7.5152647495269775, \"cold\": false, \"start\": 1680113417.4086213, \"end\": 1680113424.923886}}","success":true,"duration_us":7516108},"function_output":{"body":{"cold":false,"start":1680113417.4086213,"end":1680113424.923886,"latency":7.5152647495269775}},"client_latency_us":7517454,"function_name":"video_processing-0","function_version":"0.0.1","tid":"3d3803bato1fb9to4b40to84b2to12be796d66dc","invoke_start":"2023-03-29 14:10:17.407609953"},{"worker_response":{"json_result":"{\"body\": {\"network\": 4.5806262493133545, \"serialization\": 4.580626964569092, \"latency\": 4.580627202987671, \"cold\": false, \"start\": 1680113418.4375043, \"end\": 1680113423.0181315, \"url\": \"http://v-020.victor.futuresystems.org:8080/1G_file.log\"}}","success":true,"duration_us":4581842},"function_output":{"body":{"cold":false,"start":1680113418.4375043,"end":1680113423.0181315,"latency":4.580627202987671}},"client_latency_us":4583228,"function_name":"fetch_1gfile-0","function_version":"0.0.1","tid":"7042465cto0f50to2d74to5658toc94becc4fbb0","invoke_start":"2023-03-29 14:10:18.436481454"},{"worker_response":{"json_result":"{\"body\": {\"latency\": 7.42277717590332, \"cold\": false, \"start\": 1680113419.8644354, \"end\": 1680113427.2872126}}","success":true,"duration_us":7423628},"function_output":{"body":{"cold":false,"start":1680113419.8644354,"end":1680113427.2872126,"latency":7.42277717590332}},"client_latency_us":7497830,"function_name":"video_processing-0","function_version":"0.0.1","tid":"f0e8d5c0to7549to58beto1402to50c648b5f6a8","invoke_start":"2023-03-29 14:10:19.790502185"},{"worker_response":{"json_result":"{\"body\": {\"network\": 4.484733581542969, \"serialization\": 4.484734296798706, \"latency\": 4.484734535217285, \"cold\": false, \"start\": 1680113424.7383046, \"end\": 1680113429.2230392, \"url\": \"http://v-020.victor.futuresystems.org:8080/1G_file.log\"}}","success":true,"duration_us":4485931},"function_output":{"body":{"cold":false,"start":1680113424.7383046,"end":1680113429.2230392,"latency":4.484734535217285}},"client_latency_us":4487139,"function_name":"fetch_1gfile-0","function_version":"0.0.1","tid":"6d628ba8toecb2to9994to4f64to33b80e8eb1e3","invoke_start":"2023-03-29 14:10:24.737472675"},{"worker_response":{"json_result":"{\"body\": {\"latency\": 6.774775981903076, \"cold\": false, \"start\": 1680113430.7892594, \"end\": 1680113437.5640354}}","success":true,"duration_us":6775587},"function_output":{"body":{"cold":false,"start":1680113430.7892594,"end":1680113437.5640354,"latency":6.774775981903076}},"client_latency_us":6776837,"function_name":"video_processing-0","function_version":"0.0.1","tid":"fbad5764toafecto9861tob58dto481a15dd5777","invoke_start":"2023-03-29 14:10:30.788470688"},{"worker_response":{"json_result":"{\"body\": {\"network\": 4.4810450077056885, \"serialization\": 4.481045722961426, \"latency\": 4.481045961380005, \"cold\": false, \"start\": 1680113449.1143105, \"end\": 1680113453.5953565, \"url\": \"http://v-020.victor.futuresystems.org:8080/1G_file.log\"}}","success":true,"duration_us":4482284},"function_output":{"body":{"cold":false,"start":1680113449.1143105,"end":1680113453.5953565,"latency":4.481045961380005}},"client_latency_us":4483481,"function_name":"fetch_1gfile-0","function_version":"0.0.1","tid":"fa0de4f3to8741to5322to60edtof39c9b0fff8b","invoke_start":"2023-03-29 14:10:49.113501122"},{"worker_response":{"json_result":"{\"body\": {\"latency\": 10.829639673233032, \"cold\": false, \"start\": 1680113450.9652731, \"end\": 1680113461.7949128}}","success":true,"duration_us":10830585},"function_output":{"body":{"cold":false,"start":1680113450.9652731,"end":1680113461.7949128,"latency":10.829639673233032}},"client_latency_us":10886776,"function_name":"video_processing-0","function_version":"0.0.1","tid":"fac10fcctoefbato5431to2157to0036eae3e7b3","invoke_start":"2023-03-29 14:10:50.909464848"},{"worker_response":{"json_result":"{\"body\": {\"result\": \"2122317824 bytes (2024.0 MBs), 4.670268535614014 s, 433.3797905978224 MB/s\", \"latency\": 4.670268535614014, \"cold\": false, \"start\": 1680113457.7248092, \"end\": 1680113462.3950777}}","success":true,"duration_us":4797720},"function_output":{"body":{"cold":false,"start":1680113457.7248092,"end":1680113462.3950777,"latency":4.670268535614014}},"client_latency_us":4799795,"function_name":"dd-0","function_version":"0.0.1","tid":"fb729ad5toef52to3e7btoedddtodbf87e6806a3","invoke_start":"2023-03-29 14:10:57.637473831"},{"worker_response":{"json_result":"{\"body\": {\"result\": \"2122317824 bytes (2024.0 MBs), 4.617733478546143 s, 438.31026831744316 MB/s\", \"latency\": 4.617733478546143, \"cold\": false, \"start\": 1680113458.3039715, \"end\": 1680113462.921705}}","success":true,"duration_us":4684146},"function_output":{"body":{"cold":false,"start":1680113458.3039715,"end":1680113462.921705,"latency":4.617733478546143}},"client_latency_us":4685326,"function_name":"dd-0","function_version":"0.0.1","tid":"fea5dc56to1ce0tob51btoba2ato23b5eda20dfe","invoke_start":"2023-03-29 14:10:58.265461945"},{"worker_response":{"json_result":"{\"body\": {\"result\": \"2122317824 bytes (2024.0 MBs), 4.546054124832153 s, 445.22127199150515 MB/s\", \"latency\": 4.546054124832153, \"cold\": false, \"start\": 1680113463.2279532, \"end\": 1680113467.7740073}}","success":true,"duration_us":4600890},"function_output":{"body":{"cold":false,"start":1680113463.2279532,"end":1680113467.774007,"latency":4.546054124832153}},"client_latency_us":4602110,"function_name":"dd-0","function_version":"0.0.1","tid":"53447432todf9etoe85eto977ctoea1042d6f22d","invoke_start":"2023-03-29 14:11:03.199465975"},{"worker_response":{"json_result":"{\"body\": {\"network\": 4.502370357513428, \"serialization\": 4.502371072769165, \"latency\": 4.502371311187744, \"cold\": false, \"start\": 1680113469.6664445, \"end\": 1680113474.1688159, \"url\": \"http://v-020.victor.futuresystems.org:8080/1G_file.log\"}}","success":true,"duration_us":4503897},"function_output":{"body":{"cold":false,"start":1680113469.6664443,"end":1680113474.168816,"latency":4.502371311187744}},"client_latency_us":4505118,"function_name":"fetch_1gfile-0","function_version":"0.0.1","tid":"104efdb3tod39ftodee7to1071to77ece20723ab","invoke_start":"2023-03-29 14:11:09.665611387"},{"worker_response":{"json_result":"{\"body\": {\"result\": \"2122317824 bytes (2024.0 MBs), 4.591341972351074 s, 440.8297208503458 MB/s\", \"latency\": 4.591341972351074, \"cold\": false, \"start\": 1680113470.547946, \"end\": 1680113475.139288}}","success":true,"duration_us":4655770},"function_output":{"body":{"cold":false,"start":1680113470.547946,"end":1680113475.139288,"latency":4.591341972351074}},"client_latency_us":4698743,"function_name":"dd-0","function_version":"0.0.1","tid":"07165288to8e30to1f13to8050to52b9495acde6","invoke_start":"2023-03-29 14:11:10.478416437"},{"worker_response":{"json_result":"{\"body\": {\"result\": \"2122317824 bytes (2024.0 MBs), 4.853913307189941 s, 416.9831375030773 MB/s\", \"latency\": 4.853913307189941, \"cold\": false, \"start\": 1680113473.3806372, \"end\": 1680113478.2345505}}","success":true,"duration_us":4910194},"function_output":{"body":{"cold":false,"start":1680113473.3806372,"end":1680113478.2345505,"latency":4.853913307189941}},"client_latency_us":4978395,"function_name":"dd-0","function_version":"0.0.1","tid":"566fa613to2e55to3181todea7to948dde4c5721","invoke_start":"2023-03-29 14:11:13.290402894"},{"worker_response":{"json_result":"{\"body\": {\"network\": 4.93903374671936, \"serialization\": 4.9390339851379395, \"latency\": 4.939034461975098, \"cold\": false, \"start\": 1680113473.6800373, \"end\": 1680113478.6190717, \"url\": \"http://v-020.victor.futuresystems.org:8080/1G_file.log\"}}","success":true,"duration_us":4940199},"function_output":{"body":{"cold":false,"start":1680113473.6800373,"end":1680113478.6190715,"latency":4.939034461975098}},"client_latency_us":5010142,"function_name":"fetch_1gfile-0","function_version":"0.0.1","tid":"0a150dcfto3fc5to7d4fto0ba8tob6ef69c0c8e8","invoke_start":"2023-03-29 14:11:13.610475652"},{"worker_response":{"json_result":"{\"body\": {\"result\": \"2122317824 bytes (2024.0 MBs), 4.634025812149048 s, 436.7692546497409 MB/s\", \"latency\": 4.634025812149048, \"cold\": true, \"start\": 1680113475.3996234, \"end\": 1680113480.0336492}}","success":true,"duration_us":4735185},"function_output":{"body":{"cold":true,"start":1680113475.3996234,"end":1680113480.0336492,"latency":4.634025812149048}},"client_latency_us":5204808,"function_name":"dd-0","function_version":"0.0.1","tid":"32e6e628to1235to861dtoe2dftoaa30da1ebbc9","invoke_start":"2023-03-29 14:11:14.883468285"},{"worker_response":{"json_result":"{\"body\": {\"latency\": 10.93651008605957, \"cold\": false, \"start\": 1680113475.2973042, \"end\": 1680113486.2338142}}","success":true,"duration_us":10937357},"function_output":{"body":{"cold":false,"start":1680113475.2973042,"end":1680113486.2338142,"latency":10.93651008605957}},"client_latency_us":11007583,"function_name":"video_processing-0","function_version":"0.0.1","tid":"7552ce64to7a10todab0to08deto6378319a1165","invoke_start":"2023-03-29 14:11:15.227448792"},{"worker_response":{"json_result":"{\"body\": {\"result\": \"2122317824 bytes (2024.0 MBs), 4.568345546722412 s, 443.04879727238045 MB/s\", \"latency\": 4.568345546722412, \"cold\": false, \"start\": 1680113478.948309, \"end\": 1680113483.5166545}}","success":true,"duration_us":4658485},"function_output":{"body":{"cold":false,"start":1680113478.948309,"end":1680113483.5166545,"latency":4.568345546722412}},"client_latency_us":4659655,"function_name":"dd-0","function_version":"0.0.1","tid":"8d0398cdto9d4bto2d7cto52acto2951903ddedf","invoke_start":"2023-03-29 14:11:18.927466668"},{"worker_response":{"json_result":"{\"body\": {\"network\": 6.652495861053467, \"serialization\": 6.6524977684021, \"latency\": 6.652498006820679, \"cold\": false, \"start\": 1680113479.1861591, \"end\": 1680113485.8386571, \"url\": \"http://v-020.victor.futuresystems.org:8080/1G_file.log\"}}","success":true,"duration_us":6653574},"function_output":{"body":{"cold":false,"start":1680113479.1861591,"end":1680113485.8386571,"latency":6.652498006820679}},"client_latency_us":6654634,"function_name":"fetch_1gfile-0","function_version":"0.0.1","tid":"8482f153to5447to1e00tobcc4to5506add6be8d","invoke_start":"2023-03-29 14:11:19.185502333"},{"worker_response":{"json_result":"{\"body\": {\"network\": 8.859445571899414, \"serialization\": 8.859445810317993, \"latency\": 8.859446287155151, \"cold\": false, \"start\": 1680113479.4104621, \"end\": 1680113488.2699084, \"url\": \"http://v-020.victor.futuresystems.org:8080/1G_file.log\"}}","success":true,"duration_us":8861484},"function_output":{"body":{"cold":false,"start":1680113479.410462,"end":1680113488.2699084,"latency":8.859446287155151}},"client_latency_us":8874960,"function_name":"fetch_1gfile-0","function_version":"0.0.1","tid":"1753c4eatodc5cto72aato96f7toed23913d199f","invoke_start":"2023-03-29 14:11:19.397445786"},{"worker_response":{"json_result":"{\"body\": {\"result\": \"2122317824 bytes (2024.0 MBs), 4.77344012260437 s, 424.0128603301121 MB/s\", \"latency\": 4.77344012260437, \"cold\": false, \"start\": 1680113480.0985782, \"end\": 1680113484.8720183}}","success":true,"duration_us":4830806},"function_output":{"body":{"cold":false,"start":1680113480.0985782,"end":1680113484.8720183,"latency":4.77344012260437}},"client_latency_us":4883273,"function_name":"dd-0","function_version":"0.0.1","tid":"3203bc95to2c47to969eto6f6btod9c29753da93","invoke_start":"2023-03-29 14:11:20.028465462"},{"worker_response":{"json_result":"{\"body\": {\"latency\": 9.27955675125122, \"cold\": false, \"start\": 1680113481.0278704, \"end\": 1680113490.3074272}}","success":true,"duration_us":9280379},"function_output":{"body":{"cold":false,"start":1680113481.0278704,"end":1680113490.3074272,"latency":9.27955675125122}},"client_latency_us":9336181,"function_name":"video_processing-0","function_version":"0.0.1","tid":"44ed79e9toe3c0toa31ctodfddtob7658817e1cd","invoke_start":"2023-03-29 14:11:20.972457963"},{"worker_response":{"json_result":"{\"body\": {\"result\": \"2122317824 bytes (2024.0 MBs), 4.692229747772217 s, 431.35142752994085 MB/s\", \"latency\": 4.692229747772217, \"cold\": false, \"start\": 1680113481.996984, \"end\": 1680113486.6892138}}","success":true,"duration_us":4745878},"function_output":{"body":{"cold":false,"start":1680113481.996984,"end":1680113486.6892138,"latency":4.692229747772217}},"client_latency_us":4812989,"function_name":"dd-0","function_version":"0.0.1","tid":"0ed68c2ato015atoa556to0a06to3db0d623e097","invoke_start":"2023-03-29 14:11:21.913448679"},{"worker_response":{"json_result":"{\"body\": {\"result\": \"2122317824 bytes (2024.0 MBs), 4.689387321472168 s, 431.61288698255646 MB/s\", \"latency\": 4.689387321472168, \"cold\": false, \"start\": 1680113485.2146227, \"end\": 1680113489.90401}}","success":true,"duration_us":4744633},"function_output":{"body":{"cold":false,"start":1680113485.2146227,"end":1680113489.90401,"latency":4.689387321472168}},"client_latency_us":4802460,"function_name":"dd-0","function_version":"0.0.1","tid":"e946d8dato552ato76b2to2af0to09183db22f3b","invoke_start":"2023-03-29 14:11:25.126467136"},{"worker_response":{"json_result":"{\"body\": {\"result\": \"2122317824 bytes (2024.0 MBs), 4.613510370254517 s, 438.7114881218617 MB/s\", \"latency\": 4.613510370254517, \"cold\": false, \"start\": 1680113489.426548, \"end\": 1680113494.0400584}}","success":true,"duration_us":4660101},"function_output":{"body":{"cold":false,"start":1680113489.426548,"end":1680113494.0400584,"latency":4.613510370254517}},"client_latency_us":4661257,"function_name":"dd-0","function_version":"0.0.1","tid":"c03e1d79toc0a5tob788to398fto1345ddb63ba1","invoke_start":"2023-03-29 14:11:29.406460364"},{"worker_response":{"json_result":"{\"body\": {\"latency\": 7.322368621826172, \"cold\": false, \"start\": 1680113489.9211845, \"end\": 1680113497.2435532}}","success":true,"duration_us":7323223},"function_output":{"body":{"cold":false,"start":1680113489.9211843,"end":1680113497.2435532,"latency":7.322368621826172}},"client_latency_us":7324344,"function_name":"video_processing-0","function_version":"0.0.1","tid":"d0f7aed7to6d54to3412toe471to5bbbb8a2464f","invoke_start":"2023-03-29 14:11:29.920450169"},{"worker_response":{"json_result":"{\"body\": {\"network\": 4.494319200515747, \"serialization\": 4.494319915771484, \"latency\": 4.4943201541900635, \"cold\": false, \"start\": 1680113493.6531684, \"end\": 1680113498.1474886, \"url\": \"http://v-020.victor.futuresystems.org:8080/1G_file.log\"}}","success":true,"duration_us":4495819},"function_output":{"body":{"cold":false,"start":1680113493.6531684,"end":1680113498.1474886,"latency":4.4943201541900635}},"client_latency_us":4497006,"function_name":"fetch_1gfile-0","function_version":"0.0.1","tid":"1fc95deeto5438to8117to41c3to419c153b74c9","invoke_start":"2023-03-29 14:11:33.652468693"},{"worker_response":{"json_result":"{\"body\": {\"result\": \"2122317824 bytes (2024.0 MBs), 4.547958135604858 s, 445.0348793131133 MB/s\", \"latency\": 4.547958135604858, \"cold\": false, \"start\": 1680113500.153453, \"end\": 1680113504.7014112}}","success":true,"duration_us":4605077},"function_output":{"body":{"cold":false,"start":1680113500.153453,"end":1680113504.7014112,"latency":4.547958135604858}},"client_latency_us":4606327,"function_name":"dd-0","function_version":"0.0.1","tid":"8c367533to5b15toc5cetoe560to70eead38ee17","invoke_start":"2023-03-29 14:11:40.123471713"},{"worker_response":{"json_result":"{\"body\": {\"network\": 4.466145277023315, \"serialization\": 4.466145992279053, \"latency\": 4.466146230697632, \"cold\": false, \"start\": 1680113500.6520784, \"end\": 1680113505.1182246, \"url\": \"http://v-020.victor.futuresystems.org:8080/1G_file.log\"}}","success":true,"duration_us":4467326},"function_output":{"body":{"cold":false,"start":1680113500.6520784,"end":1680113505.1182246,"latency":4.466146230697632}},"client_latency_us":4468398,"function_name":"fetch_1gfile-0","function_version":"0.0.1","tid":"4b70d5b1to749cto9e18to69f5tob411b8f992d1","invoke_start":"2023-03-29 14:11:40.651446627"},{"worker_response":{"json_result":"{\"body\": {\"network\": 4.479498386383057, \"serialization\": 4.479499101638794, \"latency\": 4.479499101638794, \"cold\": false, \"start\": 1680113506.1612391, \"end\": 1680113510.6407382, \"url\": \"http://v-020.victor.futuresystems.org:8080/1G_file.log\"}}","success":true,"duration_us":4480820},"function_output":{"body":{"cold":false,"start":1680113506.1612391,"end":1680113510.6407382,"latency":4.479499101638794}},"client_latency_us":4482108,"function_name":"fetch_1gfile-0","function_version":"0.0.1","tid":"953d8996todd44toda38to7323toc35b45b881cc","invoke_start":"2023-03-29 14:11:46.16046938"},{"worker_response":{"json_result":"{\"body\": {\"latency\": 7.115469217300415, \"cold\": false, \"start\": 1680113508.1701555, \"end\": 1680113515.2856247}}","success":true,"duration_us":7116345},"function_output":{"body":{"cold":false,"start":1680113508.1701555,"end":1680113515.2856247,"latency":7.115469217300415}},"client_latency_us":7173530,"function_name":"video_processing-0","function_version":"0.0.1","tid":"8410a7bato2c3ato3375to5876tob299ec04982e","invoke_start":"2023-03-29 14:11:48.113466155"},{"worker_response":{"json_result":"{\"body\": {\"latency\": 6.477166652679443, \"cold\": false, \"start\": 1680113511.1960719, \"end\": 1680113517.6732385}}","success":true,"duration_us":6477932},"function_output":{"body":{"cold":false,"start":1680113511.196072,"end":1680113517.6732385,"latency":6.477166652679443}},"client_latency_us":6479088,"function_name":"video_processing-0","function_version":"0.0.1","tid":"8e028813to60e0to8ca4to1380to19282e917acc","invoke_start":"2023-03-29 14:11:51.19546896"},{"worker_response":{"json_result":"{\"body\": {\"network\": 4.499711036682129, \"serialization\": 4.499711036682129, \"latency\": 4.499711513519287, \"cold\": false, \"start\": 1680113516.8332996, \"end\": 1680113521.3330112, \"url\": \"http://v-020.victor.futuresystems.org:8080/1G_file.log\"}}","success":true,"duration_us":4501040},"function_output":{"body":{"cold":false,"start":1680113516.8332996,"end":1680113521.3330112,"latency":4.499711513519287}},"client_latency_us":4502210,"function_name":"fetch_1gfile-0","function_version":"0.0.1","tid":"2699b680toc6a5to0d07to17c3tod254c6ba146a","invoke_start":"2023-03-29 14:11:56.832482394"},{"worker_response":{"json_result":"{\"body\": {\"latency\": 6.917831182479858, \"cold\": false, \"start\": 1680113518.2278137, \"end\": 1680113525.145645}}","success":true,"duration_us":6918564},"function_output":{"body":{"cold":false,"start":1680113518.2278135,"end":1680113525.145645,"latency":6.917831182479858}},"client_latency_us":6987455,"function_name":"video_processing-0","function_version":"0.0.1","tid":"dc705640toa7e1to46fdto0ef3to0068cc87b818","invoke_start":"2023-03-29 14:11:58.159467308"},{"worker_response":{"json_result":"{\"body\": {\"latency\": 10.957494020462036, \"cold\": false, \"start\": 1680113521.1584945, \"end\": 1680113532.1159885}}","success":true,"duration_us":10958319},"function_output":{"body":{"cold":false,"start":1680113521.1584945,"end":1680113532.1159885,"latency":10.957494020462036}},"client_latency_us":11008900,"function_name":"video_processing-0","function_version":"0.0.1","tid":"13069a1eto2613to6a09to3f83toe66b50196d94","invoke_start":"2023-03-29 14:12:01.10847269"},{"worker_response":{"json_result":"{\"body\": {\"network\": 4.5094382762908936, \"serialization\": 4.509439468383789, \"latency\": 4.509439706802368, \"cold\": false, \"start\": 1680113524.973181, \"end\": 1680113529.4826207, \"url\": \"http://v-020.victor.futuresystems.org:8080/1G_file.log\"}}","success":true,"duration_us":4510928},"function_output":{"body":{"cold":false,"start":1680113524.973181,"end":1680113529.4826207,"latency":4.509439706802368}},"client_latency_us":4512218,"function_name":"fetch_1gfile-0","function_version":"0.0.1","tid":"9e9da49bto8ee7to2796to5908to140e72f02c5b","invoke_start":"2023-03-29 14:12:04.972470912"},{"worker_response":{"json_result":"{\"body\": {\"result\": \"2122317824 bytes (2024.0 MBs), 4.701877117156982 s, 430.46637535772595 MB/s\", \"latency\": 4.701877117156982, \"cold\": false, \"start\": 1680113527.331744, \"end\": 1680113532.033621}}","success":true,"duration_us":4779947},"function_output":{"body":{"cold":false,"start":1680113527.331744,"end":1680113532.033621,"latency":4.701877117156982}},"client_latency_us":4840141,"function_name":"dd-0","function_version":"0.0.1","tid":"fe79edaftofbb0to00e5to1d5atod8badfba10c8","invoke_start":"2023-03-29 14:12:07.242478731"},{"worker_response":{"json_result":"{\"body\": {\"result\": \"2122317824 bytes (2024.0 MBs), 6.292279243469238 s, 321.6640459974359 MB/s\", \"latency\": 6.292279243469238, \"cold\": false, \"start\": 1680113529.3954532, \"end\": 1680113535.6877325}}","success":true,"duration_us":6370743},"function_output":{"body":{"cold":false,"start":1680113529.3954532,"end":1680113535.6877325,"latency":6.292279243469238}},"client_latency_us":6443425,"function_name":"dd-0","function_version":"0.0.1","tid":"8ad47992tob4a5to0c05toc859tofd8c453ddf70","invoke_start":"2023-03-29 14:12:09.304578104"},{"worker_response":{"json_result":"{\"body\": {\"latency\": 6.373999834060669, \"cold\": false, \"start\": 1680113529.699143, \"end\": 1680113536.0731428}}","success":true,"duration_us":6374840},"function_output":{"body":{"cold":false,"start":1680113529.699143,"end":1680113536.0731428,"latency":6.373999834060669}},"client_latency_us":6376027,"function_name":"video_processing-0","function_version":"0.0.1","tid":"438744dcto0f55toac7dtod5e4to050e3a42a736","invoke_start":"2023-03-29 14:12:09.698447532"},{"worker_response":{"json_result":"{\"body\": {\"result\": \"2122317824 bytes (2024.0 MBs), 4.556435823440552 s, 444.2068490436201 MB/s\", \"latency\": 4.556435823440552, \"cold\": false, \"start\": 1680113535.829046, \"end\": 1680113540.3854818}}","success":true,"duration_us":4610713},"function_output":{"body":{"cold":false,"start":1680113535.829046,"end":1680113540.3854818,"latency":4.556435823440552}},"client_latency_us":4612078,"function_name":"dd-0","function_version":"0.0.1","tid":"2f717307tobeecto9d6fto83e5to52530b10a7ea","invoke_start":"2023-03-29 14:12:15.798451972"},{"worker_response":{"json_result":"{\"body\": {\"network\": 4.467814683914185, \"serialization\": 4.467815160751343, \"latency\": 4.467815399169922, \"cold\": false, \"start\": 1680113543.1000948, \"end\": 1680113547.5679102, \"url\": \"http://v-020.victor.futuresystems.org:8080/1G_file.log\"}}","success":true,"duration_us":4468896},"function_output":{"body":{"cold":false,"start":1680113543.1000948,"end":1680113547.5679102,"latency":4.467815399169922}},"client_latency_us":4470025,"function_name":"fetch_1gfile-0","function_version":"0.0.1","tid":"86fc48cftoabbeto4234to5a09to86c9a1fdf13f","invoke_start":"2023-03-29 14:12:23.099474293"},{"worker_response":{"json_result":"{\"body\": {\"network\": 4.471634864807129, \"serialization\": 4.471635341644287, \"latency\": 4.471635580062866, \"cold\": false, \"start\": 1680113548.601049, \"end\": 1680113553.0726845, \"url\": \"http://v-020.victor.futuresystems.org:8080/1G_file.log\"}}","success":true,"duration_us":4472955},"function_output":{"body":{"cold":false,"start":1680113548.601049,"end":1680113553.0726843,"latency":4.471635580062866}},"client_latency_us":4474078,"function_name":"fetch_1gfile-0","function_version":"0.0.1","tid":"fadab7a3to01d3to5d28to7226to24671e4934c2","invoke_start":"2023-03-29 14:12:28.60047172"},{"worker_response":{"json_result":"{\"body\": {\"network\": 4.595134496688843, \"serialization\": 4.59513521194458, \"latency\": 4.595135927200317, \"cold\": false, \"start\": 1680113553.566363, \"end\": 1680113558.161499, \"url\": \"http://v-020.victor.futuresystems.org:8080/1G_file.log\"}}","success":true,"duration_us":4596636},"function_output":{"body":{"cold":false,"start":1680113553.566363,"end":1680113558.161499,"latency":4.595135927200317}},"client_latency_us":4597798,"function_name":"fetch_1gfile-0","function_version":"0.0.1","tid":"981ea773toe580to155cto3a45to3badb2a46c64","invoke_start":"2023-03-29 14:12:33.565466065"},{"worker_response":{"json_result":"{\"body\": {\"result\": \"2122317824 bytes (2024.0 MBs), 4.611023664474487 s, 438.948083392817 MB/s\", \"latency\": 4.611023664474487, \"cold\": false, \"start\": 1680113555.2014391, \"end\": 1680113559.8124628}}","success":true,"duration_us":4664559},"function_output":{"body":{"cold":false,"start":1680113555.2014391,"end":1680113559.8124628,"latency":4.611023664474487}},"client_latency_us":4733503,"function_name":"dd-0","function_version":"0.0.1","tid":"9271bffatob100to0840tod6c8to921ef957c0fb","invoke_start":"2023-03-29 14:12:35.106467704"},{"worker_response":{"json_result":"{\"body\": {\"network\": 5.5074238777160645, \"serialization\": 5.507424592971802, \"latency\": 5.507424831390381, \"cold\": false, \"start\": 1680113556.9891162, \"end\": 1680113562.496541, \"url\": \"http://v-020.victor.futuresystems.org:8080/1G_file.log\"}}","success":true,"duration_us":5508543},"function_output":{"body":{"cold":false,"start":1680113556.9891162,"end":1680113562.496541,"latency":5.507424831390381}},"client_latency_us":5575656,"function_name":"fetch_1gfile-0","function_version":"0.0.1","tid":"1ef877c1toaf05tod04bto6a77to9e1d0cf4cd61","invoke_start":"2023-03-29 14:12:36.922508017"}]